README.rst
setup.py
isass/__init__.py
isass/cli.py
isass/compiler.py
isass/helpers.py
isass/manifest.py
isass/watch.py
isass.egg-info/PKG-INFO
isass.egg-info/SOURCES.txt
isass.egg-info/dependency_links.txt
isass.egg-info/entry_points.txt
isass.egg-info/requires.txt
isass.egg-info/top_level.txt