Metadata-Version: 1.1
Name: isass
Version: 0.1.9
Summary: compiles indented-SASS-syntax to CSS stylesheets
Home-page: http://github.com/pylover/isass
Author: Vahid Mardani
Author-email: vahid.mardani@gmail.com
License: MIT
Platform: UNKNOWN
Classifier: Development Status :: 5 - Production/Stable
Classifier: Environment :: Console
Classifier: Intended Audience :: Developers
Classifier: License :: OSI Approved :: MIT License
Classifier: Natural Language :: English
Classifier: Operating System :: OS Independent
Classifier: Programming Language :: Python
Classifier: Topic :: Communications :: Email
Classifier: Topic :: Software Development :: Libraries
Classifier: Topic :: Utilities
